{"cameraMode":{"drawMode":0,"name":"Shaded","section":"Shading Mode"},"sceneLighting":true,"audioPlay":false,"sceneViewState":{"m_AlwaysRefresh":false,"showFog":true,"showSkybox":true,"showFlares":true,"showImageEffects":true,"showParticleSystems":true,"showVisualEffectGraphs":true,"m_FxEnabled":true},"in2DMode":false,"pivot":{"x":-13.807215690612793,"y":5.596373558044434,"z":-11.6447172164917},"rotation":{"x":-0.20249240100383759,"y":-0.6064287424087524,"z":0.16422566771507264,"w":-0.7514120936393738},"size":2.986372232437134,"orthographic":false}